deseqpyodide/__init__.py
deseqpyodide/__version__.py
deseqpyodide/dds.py
deseqpyodide/ds.py
deseqpyodide/grid_search.py
deseqpyodide/preprocessing.py
deseqpyodide/utils.py
deseqpyodide-0.0.7.dist-info/METADATA
deseqpyodide-0.0.7.dist-info/WHEEL
deseqpyodide-0.0.7.dist-info/top_level.txt
deseqpyodide-0.0.7.dist-info/RECORD
